codex/__init__.py
codex/codex.py
codex/codex_components.py
codex/codex_gui.py
hb_lcs/__init__.py
hb_lcs/cli.py
hb_lcs/documentation_generator.py
hb_lcs/ide.py
hb_lcs/ide_teachscript_integration.py
hb_lcs/identifier_validator.py
hb_lcs/interpreter_generator.py
hb_lcs/language_config.py
hb_lcs/language_runtime.py
hb_lcs/language_validator.py
hb_lcs/launch_ide.py
hb_lcs/launch_ide_teachscript.py
hb_lcs/parser_generator.py
hb_lcs/teachscript_console.py
hb_lcs/teachscript_highlighting.py
hb_lcs/teachscript_libraries.py
hb_lcs/teachscript_runtime.py
hb_lcs/test_framework.py
hb_lcs/visual_config_editor.py
parsercraft-2.0.0.dist-info/licenses/LICENSE
parsercraft-2.0.0.dist-info/METADATA
parsercraft-2.0.0.dist-info/WHEEL
parsercraft-2.0.0.dist-info/entry_points.txt
parsercraft-2.0.0.dist-info/top_level.txt
parsercraft-2.0.0.dist-info/RECORD
